{
  "video_path": "/Volumes/Expansion/summer2025_ncos_kb_collections/birds_beak/week_5/day_1/site_2/afternoon/P1000404.MP4",
  "video_name": "P1000404.MP4",
  "analysis_date": "2025-07-28T21:58:43.802049",
  "model_used": "models/object_detection/ventura_bombus_yolo/weights/best.pt",
  "confidence_threshold": 0.1,
  "video_info": {
    "duration_seconds": 1263.7625,
    "fps": 59.94005994005994,
    "total_frames": 75750
  },
  "summary": {
    "total_segments": 5,
    "active_segments": 5,
    "total_bee_detections": 235,
    "peak_segment": 4,
    "peak_detections": 85,
    "overall_activity_rate": 1.0
  },
  "segments": [
    {
      "segment_number": 1,
      "start_time": 0,
      "end_time": 300,
      "duration": 300,
      "total_detections": 36,
      "frames_with_bees": 21,
      "max_simultaneous_bees": 4,
      "detection_rate": 0.7,
      "detections": [
        {
          "timestamp": 0,
          "bee_count": 2,
          "avg_confidence": 0.21677075326442719,
          "individual_confidences": [
            0.28275027871131897,
            0.1507912278175354
          ]
        },
        {
          "timestamp": 10,
          "bee_count": 0,
          "avg_confidence": 0.0,
          "individual_confidences": []
        },
        {
          "timestamp": 20,
          "bee_count": 0,
          "avg_confidence": 0.0,
          "individual_confidences": []
        },
        {
          "timestamp": 30,
          "bee_count": 1,
          "avg_confidence": 0.10658125579357147,
          "individual_confidences": [
            0.10658125579357147
          ]
        },
        {
          "timestamp": 40,
          "bee_count": 1,
          "avg_confidence": 0.16560932993888855,
          "individual_confidences": [
            0.16560932993888855
          ]
        },
        {
          "timestamp": 50,
          "bee_count": 2,
          "avg_confidence": 0.12753262370824814,
          "individual_confidences": [
            0.13236947357654572,
            0.12269577383995056
          ]
        },
        {
          "timestamp": 60,
          "bee_count": 2,
          "avg_confidence": 0.1592925414443016,
          "individual_confidences": [
            0.1619374305009842,
            0.15664765238761902
          ]
        },
        {
          "timestamp": 70,
          "bee_count": 0,
          "avg_confidence": 0.0,
          "individual_confidences": []
        },
        {
          "timestamp": 80,
          "bee_count": 1,
          "avg_confidence": 0.18403750658035278,
          "individual_confidences": [
            0.18403750658035278
          ]
        },
        {
          "timestamp": 90,
          "bee_count": 1,
          "avg_confidence": 0.22186215221881866,
          "individual_confidences": [
            0.22186215221881866
          ]
        },
        {
          "timestamp": 100,
          "bee_count": 1,
          "avg_confidence": 0.12941975891590118,
          "individual_confidences": [
            0.12941975891590118
          ]
        },
        {
          "timestamp": 110,
          "bee_count": 0,
          "avg_confidence": 0.0,
          "individual_confidences": []
        },
        {
          "timestamp": 120,
          "bee_count": 0,
          "avg_confidence": 0.0,
          "individual_confidences": []
        },
        {
          "timestamp": 130,
          "bee_count": 1,
          "avg_confidence": 0.12196613103151321,
          "individual_confidences": [
            0.12196613103151321
          ]
        },
        {
          "timestamp": 140,
          "bee_count": 0,
          "avg_confidence": 0.0,
          "individual_confidences": []
        },
        {
          "timestamp": 150,
          "bee_count": 4,
          "avg_confidence": 0.12581843324005604,
          "individual_confidences": [
            0.16007405519485474,
            0.12742425501346588,
            0.10962434113025665,
            0.10615108162164688
          ]
        },
        {
          "timestamp": 160,
          "bee_count": 2,
          "avg_confidence": 0.11887812986969948,
          "individual_confidences": [
            0.12760113179683685,
            0.1101551279425621
          ]
        },
        {
          "timestamp": 170,
          "bee_count": 1,
          "avg_confidence": 0.11457927525043488,
          "individual_confidences": [
            0.11457927525043488
          ]
        },
        {
          "timestamp": 180,
          "bee_count": 1,
          "avg_confidence": 0.24454820156097412,
          "individual_confidences": [
            0.24454820156097412
          ]
        },
        {
          "timestamp": 190,
          "bee_count": 1,
          "avg_confidence": 0.10364429652690887,
          "individual_confidences": [
            0.10364429652690887
          ]
        },
        {
          "timestamp": 200,
          "bee_count": 1,
          "avg_confidence": 0.1272481232881546,
          "individual_confidences": [
            0.1272481232881546
          ]
        },
        {
          "timestamp": 210,
          "bee_count": 2,
          "avg_confidence": 0.1346493549644947,
          "individual_confidences": [
            0.15316717326641083,
            0.11613153666257858
          ]
        },
        {
          "timestamp": 220,
          "bee_count": 0,
          "avg_confidence": 0.0,
          "individual_confidences": []
        },
        {
          "timestamp": 230,
          "bee_count": 2,
          "avg_confidence": 0.18190976232290268,
          "individual_confidences": [
            0.21251779794692993,
            0.15130172669887543
          ]
        },
        {
          "timestamp": 240,
          "bee_count": 3,
          "avg_confidence": 0.10783129433790843,
          "individual_confidences": [
            0.109979547560215,
            0.10937061160802841,
            0.10414372384548187
          ]
        },
        {
          "timestamp": 250,
          "bee_count": 2,
          "avg_confidence": 0.11494579911231995,
          "individual_confidences": [
            0.11597288399934769,
            0.1139187142252922
          ]
        },
        {
          "timestamp": 260,
          "bee_count": 3,
          "avg_confidence": 0.20881428817907968,
          "individual_confidences": [
            0.2879003584384918,
            0.21973982453346252,
            0.11880268156528473
          ]
        },
        {
          "timestamp": 270,
          "bee_count": 0,
          "avg_confidence": 0.0,
          "individual_confidences": []
        },
        {
          "timestamp": 280,
          "bee_count": 2,
          "avg_confidence": 0.14907203614711761,
          "individual_confidences": [
            0.16503766179084778,
            0.13310641050338745
          ]
        },
        {
          "timestamp": 290,
          "bee_count": 0,
          "avg_confidence": 0.0,
          "individual_confidences": []
        }
      ]
    },
    {
      "segment_number": 2,
      "start_time": 300,
      "end_time": 600,
      "duration": 300,
      "total_detections": 52,
      "frames_with_bees": 25,
      "max_simultaneous_bees": 4,
      "detection_rate": 0.8333333333333334,
      "detections": [
        {
          "timestamp": 300,
          "bee_count": 1,
          "avg_confidence": 0.1631176918745041,
          "individual_confidences": [
            0.1631176918745041
          ]
        },
        {
          "timestamp": 310,
          "bee_count": 2,
          "avg_confidence": 0.1414266936480999,
          "individual_confidences": [
            0.16041606664657593,
            0.12243732064962387
          ]
        },
        {
          "timestamp": 320,
          "bee_count": 1,
          "avg_confidence": 0.11351536959409714,
          "individual_confidences": [
            0.11351536959409714
          ]
        },
        {
          "timestamp": 330,
          "bee_count": 2,
          "avg_confidence": 0.12759438157081604,
          "individual_confidences": [
            0.15343987941741943,
            0.10174888372421265
          ]
        },
        {
          "timestamp": 340,
          "bee_count": 3,
          "avg_confidence": 0.13411101450522742,
          "individual_confidences": [
            0.18149614334106445,
            0.12017332762479782,
            0.10066357254981995
          ]
        },
        {
          "timestamp": 350,
          "bee_count": 2,
          "avg_confidence": 0.13467233628034592,
          "individual_confidences": [
            0.1508999466896057,
            0.11844472587108612
          ]
        },
        {
          "timestamp": 360,
          "bee_count": 3,
          "avg_confidence": 0.10777148604393005,
          "individual_confidences": [
            0.12005776911973953,
            0.10283783078193665,
            0.10041885823011398
          ]
        },
        {
          "timestamp": 370,
          "bee_count": 0,
          "avg_confidence": 0.0,
          "individual_confidences": []
        },
        {
          "timestamp": 380,
          "bee_count": 0,
          "avg_confidence": 0.0,
          "individual_confidences": []
        },
        {
          "timestamp": 390,
          "bee_count": 0,
          "avg_confidence": 0.0,
          "individual_confidences": []
        },
        {
          "timestamp": 400,
          "bee_count": 2,
          "avg_confidence": 0.19663581252098083,
          "individual_confidences": [
            0.2743338942527771,
            0.11893773078918457
          ]
        },
        {
          "timestamp": 410,
          "bee_count": 2,
          "avg_confidence": 0.10803082212805748,
          "individual_confidences": [
            0.1144106462597847,
            0.10165099799633026
          ]
        },
        {
          "timestamp": 420,
          "bee_count": 3,
          "avg_confidence": 0.14305977274974188,
          "individual_confidences": [
            0.1945229321718216,
            0.126329243183136,
            0.10832714289426804
          ]
        },
        {
          "timestamp": 430,
          "bee_count": 2,
          "avg_confidence": 0.21653510630130768,
          "individual_confidences": [
            0.2900966703891754,
            0.14297354221343994
          ]
        },
        {
          "timestamp": 440,
          "bee_count": 1,
          "avg_confidence": 0.1311032474040985,
          "individual_confidences": [
            0.1311032474040985
          ]
        },
        {
          "timestamp": 450,
          "bee_count": 3,
          "avg_confidence": 0.13861743857463202,
          "individual_confidences": [
            0.1952812820672989,
            0.12011323124170303,
            0.1004578024148941
          ]
        },
        {
          "timestamp": 460,
          "bee_count": 2,
          "avg_confidence": 0.1223856545984745,
          "individual_confidences": [
            0.12316788733005524,
            0.12160342186689377
          ]
        },
        {
          "timestamp": 470,
          "bee_count": 3,
          "avg_confidence": 0.18657605350017548,
          "individual_confidences": [
            0.2651768922805786,
            0.15965937077999115,
            0.13489189743995667
          ]
        },
        {
          "timestamp": 480,
          "bee_count": 0,
          "avg_confidence": 0.0,
          "individual_confidences": []
        },
        {
          "timestamp": 490,
          "bee_count": 3,
          "avg_confidence": 0.1544585476318995,
          "individual_confidences": [
            0.18432505428791046,
            0.16049230098724365,
            0.11855828762054443
          ]
        },
        {
          "timestamp": 500,
          "bee_count": 1,
          "avg_confidence": 0.14771275222301483,
          "individual_confidences": [
            0.14771275222301483
          ]
        },
        {
          "timestamp": 510,
          "bee_count": 2,
          "avg_confidence": 0.14800767228007317,
          "individual_confidences": [
            0.1711864471435547,
            0.12482889741659164
          ]
        },
        {
          "timestamp": 520,
          "bee_count": 2,
          "avg_confidence": 0.1792013868689537,
          "individual_confidences": [
            0.20103609561920166,
            0.15736667811870575
          ]
        },
        {
          "timestamp": 530,
          "bee_count": 1,
          "avg_confidence": 0.1338147521018982,
          "individual_confidences": [
            0.1338147521018982
          ]
        },
        {
          "timestamp": 540,
          "bee_count": 0,
          "avg_confidence": 0.0,
          "individual_confidences": []
        },
        {
          "timestamp": 550,
          "bee_count": 2,
          "avg_confidence": 0.1129327118396759,
          "individual_confidences": [
            0.12462000548839569,
            0.10124541819095612
          ]
        },
        {
          "timestamp": 560,
          "bee_count": 1,
          "avg_confidence": 0.11755125224590302,
          "individual_confidences": [
            0.11755125224590302
          ]
        },
        {
          "timestamp": 570,
          "bee_count": 4,
          "avg_confidence": 0.17521996423602104,
          "individual_confidences": [
            0.21981044113636017,
            0.178769052028656,
            0.1580880880355835,
            0.1442122757434845
          ]
        },
        {
          "timestamp": 580,
          "bee_count": 3,
          "avg_confidence": 0.14476410547892252,
          "individual_confidences": [
            0.14974550902843475,
            0.14877676963806152,
            0.1357700377702713
          ]
        },
        {
          "timestamp": 590,
          "bee_count": 1,
          "avg_confidence": 0.10076440870761871,
          "individual_confidences": [
            0.10076440870761871
          ]
        }
      ]
    },
    {
      "segment_number": 3,
      "start_time": 600,
      "end_time": 900,
      "duration": 300,
      "total_detections": 46,
      "frames_with_bees": 26,
      "max_simultaneous_bees": 4,
      "detection_rate": 0.8666666666666667,
      "detections": [
        {
          "timestamp": 600,
          "bee_count": 1,
          "avg_confidence": 0.2169601023197174,
          "individual_confidences": [
            0.2169601023197174
          ]
        },
        {
          "timestamp": 610,
          "bee_count": 2,
          "avg_confidence": 0.12286511436104774,
          "individual_confidences": [
            0.13774606585502625,
            0.10798416286706924
          ]
        },
        {
          "timestamp": 620,
          "bee_count": 0,
          "avg_confidence": 0.0,
          "individual_confidences": []
        },
        {
          "timestamp": 630,
          "bee_count": 1,
          "avg_confidence": 0.13005726039409637,
          "individual_confidences": [
            0.13005726039409637
          ]
        },
        {
          "timestamp": 640,
          "bee_count": 2,
          "avg_confidence": 0.15370963886380196,
          "individual_confidences": [
            0.2064284086227417,
            0.10099086910486221
          ]
        },
        {
          "timestamp": 650,
          "bee_count": 1,
          "avg_confidence": 0.1797552853822708,
          "individual_confidences": [
            0.1797552853822708
          ]
        },
        {
          "timestamp": 660,
          "bee_count": 1,
          "avg_confidence": 0.10047124326229095,
          "individual_confidences": [
            0.10047124326229095
          ]
        },
        {
          "timestamp": 670,
          "bee_count": 0,
          "avg_confidence": 0.0,
          "individual_confidences": []
        },
        {
          "timestamp": 680,
          "bee_count": 3,
          "avg_confidence": 0.13865301261345545,
          "individual_confidences": [
            0.157342791557312,
            0.1539088487625122,
            0.10470739752054214
          ]
        },
        {
          "timestamp": 690,
          "bee_count": 1,
          "avg_confidence": 0.1415993720293045,
          "individual_confidences": [
            0.1415993720293045
          ]
        },
        {
          "timestamp": 700,
          "bee_count": 1,
          "avg_confidence": 0.12464132159948349,
          "individual_confidences": [
            0.12464132159948349
          ]
        },
        {
          "timestamp": 710,
          "bee_count": 2,
          "avg_confidence": 0.12459398433566093,
          "individual_confidences": [
            0.1463441103696823,
            0.10284385830163956
          ]
        },
        {
          "timestamp": 720,
          "bee_count": 1,
          "avg_confidence": 0.1680494099855423,
          "individual_confidences": [
            0.1680494099855423
          ]
        },
        {
          "timestamp": 730,
          "bee_count": 1,
          "avg_confidence": 0.1449020653963089,
          "individual_confidences": [
            0.1449020653963089
          ]
        },
        {
          "timestamp": 740,
          "bee_count": 2,
          "avg_confidence": 0.12371378391981125,
          "individual_confidences": [
            0.13820409774780273,
            0.10922347009181976
          ]
        },
        {
          "timestamp": 750,
          "bee_count": 3,
          "avg_confidence": 0.21200468639532724,
          "individual_confidences": [
            0.40903612971305847,
            0.11752702295780182,
            0.10945090651512146
          ]
        },
        {
          "timestamp": 760,
          "bee_count": 3,
          "avg_confidence": 0.16968795408805212,
          "individual_confidences": [
            0.2998586595058441,
            0.10918426513671875,
            0.10002093762159348
          ]
        },
        {
          "timestamp": 770,
          "bee_count": 2,
          "avg_confidence": 0.16846615821123123,
          "individual_confidences": [
            0.18725600838661194,
            0.14967630803585052
          ]
        },
        {
          "timestamp": 780,
          "bee_count": 0,
          "avg_confidence": 0.0,
          "individual_confidences": []
        },
        {
          "timestamp": 790,
          "bee_count": 1,
          "avg_confidence": 0.12539473176002502,
          "individual_confidences": [
            0.12539473176002502
          ]
        },
        {
          "timestamp": 800,
          "bee_count": 1,
          "avg_confidence": 0.14537441730499268,
          "individual_confidences": [
            0.14537441730499268
          ]
        },
        {
          "timestamp": 810,
          "bee_count": 1,
          "avg_confidence": 0.10843819379806519,
          "individual_confidences": [
            0.10843819379806519
          ]
        },
        {
          "timestamp": 820,
          "bee_count": 1,
          "avg_confidence": 0.14600226283073425,
          "individual_confidences": [
            0.14600226283073425
          ]
        },
        {
          "timestamp": 830,
          "bee_count": 0,
          "avg_confidence": 0.0,
          "individual_confidences": []
        },
        {
          "timestamp": 840,
          "bee_count": 2,
          "avg_confidence": 0.2823811396956444,
          "individual_confidences": [
            0.35111919045448303,
            0.21364308893680573
          ]
        },
        {
          "timestamp": 850,
          "bee_count": 2,
          "avg_confidence": 0.17827312648296356,
          "individual_confidences": [
            0.1992950588464737,
            0.15725119411945343
          ]
        },
        {
          "timestamp": 860,
          "bee_count": 4,
          "avg_confidence": 0.15429935976862907,
          "individual_confidences": [
            0.2079017609357834,
            0.14962369203567505,
            0.14586597681045532,
            0.11380600929260254
          ]
        },
        {
          "timestamp": 870,
          "bee_count": 2,
          "avg_confidence": 0.39723071455955505,
          "individual_confidences": [
            0.6384698152542114,
            0.15599161386489868
          ]
        },
        {
          "timestamp": 880,
          "bee_count": 3,
          "avg_confidence": 0.14605739464362463,
          "individual_confidences": [
            0.18060825765132904,
            0.153075709939003,
            0.10448821634054184
          ]
        },
        {
          "timestamp": 890,
          "bee_count": 2,
          "avg_confidence": 0.12498626857995987,
          "individual_confidences": [
            0.13536016643047333,
            0.11461237072944641
          ]
        }
      ]
    },
    {
      "segment_number": 4,
      "start_time": 900,
      "end_time": 1200,
      "duration": 300,
      "total_detections": 85,
      "frames_with_bees": 29,
      "max_simultaneous_bees": 5,
      "detection_rate": 0.9666666666666667,
      "detections": [
        {
          "timestamp": 900,
          "bee_count": 3,
          "avg_confidence": 0.301022507250309,
          "individual_confidences": [
            0.6447339057922363,
            0.13892421126365662,
            0.11940940469503403
          ]
        },
        {
          "timestamp": 910,
          "bee_count": 2,
          "avg_confidence": 0.10470293462276459,
          "individual_confidences": [
            0.10685412585735321,
            0.10255174338817596
          ]
        },
        {
          "timestamp": 920,
          "bee_count": 1,
          "avg_confidence": 0.12345259636640549,
          "individual_confidences": [
            0.12345259636640549
          ]
        },
        {
          "timestamp": 930,
          "bee_count": 3,
          "avg_confidence": 0.16004073868195215,
          "individual_confidences": [
            0.2428552806377411,
            0.13513384759426117,
            0.10213308781385422
          ]
        },
        {
          "timestamp": 940,
          "bee_count": 5,
          "avg_confidence": 0.1427154839038849,
          "individual_confidences": [
            0.2337610274553299,
            0.1497969925403595,
            0.12255988270044327,
            0.10561253130435944,
            0.10184698551893234
          ]
        },
        {
          "timestamp": 950,
          "bee_count": 3,
          "avg_confidence": 0.12933087348937988,
          "individual_confidences": [
            0.153760626912117,
            0.12862077355384827,
            0.10561122000217438
          ]
        },
        {
          "timestamp": 960,
          "bee_count": 1,
          "avg_confidence": 0.21278168261051178,
          "individual_confidences": [
            0.21278168261051178
          ]
        },
        {
          "timestamp": 970,
          "bee_count": 1,
          "avg_confidence": 0.12417421489953995,
          "individual_confidences": [
            0.12417421489953995
          ]
        },
        {
          "timestamp": 980,
          "bee_count": 2,
          "avg_confidence": 0.1257365234196186,
          "individual_confidences": [
            0.1491851508617401,
            0.1022878959774971
          ]
        },
        {
          "timestamp": 990,
          "bee_count": 4,
          "avg_confidence": 0.15086037106812,
          "individual_confidences": [
            0.1768776923418045,
            0.17191903293132782,
            0.13055624067783356,
            0.12408851832151413
          ]
        },
        {
          "timestamp": 1000,
          "bee_count": 4,
          "avg_confidence": 0.13538016192615032,
          "individual_confidences": [
            0.14719544351100922,
            0.13704682886600494,
            0.13695013523101807,
            0.12032824009656906
          ]
        },
        {
          "timestamp": 1010,
          "bee_count": 4,
          "avg_confidence": 0.16243299841880798,
          "individual_confidences": [
            0.20345185697078705,
            0.18199452757835388,
            0.1562667191028595,
            0.1080188900232315
          ]
        },
        {
          "timestamp": 1020,
          "bee_count": 5,
          "avg_confidence": 0.14518008828163148,
          "individual_confidences": [
            0.1974349468946457,
            0.17320255935192108,
            0.12927433848381042,
            0.1214166134595871,
            0.10457198321819305
          ]
        },
        {
          "timestamp": 1030,
          "bee_count": 4,
          "avg_confidence": 0.16597670689225197,
          "individual_confidences": [
            0.2214152216911316,
            0.18312488496303558,
            0.15571852028369904,
            0.10364820063114166
          ]
        },
        {
          "timestamp": 1040,
          "bee_count": 4,
          "avg_confidence": 0.16100863739848137,
          "individual_confidences": [
            0.24421748518943787,
            0.13357330858707428,
            0.13316458463668823,
            0.1330791711807251
          ]
        },
        {
          "timestamp": 1050,
          "bee_count": 2,
          "avg_confidence": 0.17191842198371887,
          "individual_confidences": [
            0.19367091357707977,
            0.15016593039035797
          ]
        },
        {
          "timestamp": 1060,
          "bee_count": 1,
          "avg_confidence": 0.15796442329883575,
          "individual_confidences": [
            0.15796442329883575
          ]
        },
        {
          "timestamp": 1070,
          "bee_count": 3,
          "avg_confidence": 0.12996335327625275,
          "individual_confidences": [
            0.15517383813858032,
            0.11800693720579147,
            0.11670928448438644
          ]
        },
        {
          "timestamp": 1080,
          "bee_count": 0,
          "avg_confidence": 0.0,
          "individual_confidences": []
        },
        {
          "timestamp": 1090,
          "bee_count": 3,
          "avg_confidence": 0.1432664766907692,
          "individual_confidences": [
            0.1820417195558548,
            0.1412697285413742,
            0.10648798197507858
          ]
        },
        {
          "timestamp": 1100,
          "bee_count": 4,
          "avg_confidence": 0.1157095916569233,
          "individual_confidences": [
            0.1339380443096161,
            0.11851658672094345,
            0.10924596339464188,
            0.10113777220249176
          ]
        },
        {
          "timestamp": 1110,
          "bee_count": 3,
          "avg_confidence": 0.14016659557819366,
          "individual_confidences": [
            0.14973093569278717,
            0.1446775645017624,
            0.12609128654003143
          ]
        },
        {
          "timestamp": 1120,
          "bee_count": 2,
          "avg_confidence": 0.15768272429704666,
          "individual_confidences": [
            0.17774710059165955,
            0.13761834800243378
          ]
        },
        {
          "timestamp": 1130,
          "bee_count": 2,
          "avg_confidence": 0.25429631024599075,
          "individual_confidences": [
            0.3070923089981079,
            0.2015003114938736
          ]
        },
        {
          "timestamp": 1140,
          "bee_count": 4,
          "avg_confidence": 0.1691917609423399,
          "individual_confidences": [
            0.3029335141181946,
            0.13426096737384796,
            0.12505176663398743,
            0.11452079564332962
          ]
        },
        {
          "timestamp": 1150,
          "bee_count": 3,
          "avg_confidence": 0.13843967765569687,
          "individual_confidences": [
            0.19575272500514984,
            0.11343314498662949,
            0.10613316297531128
          ]
        },
        {
          "timestamp": 1160,
          "bee_count": 3,
          "avg_confidence": 0.15328693886597952,
          "individual_confidences": [
            0.20403970777988434,
            0.15402841567993164,
            0.10179269313812256
          ]
        },
        {
          "timestamp": 1170,
          "bee_count": 4,
          "avg_confidence": 0.14969449490308762,
          "individual_confidences": [
            0.19227351248264313,
            0.18851734697818756,
            0.11052261292934418,
            0.1074645072221756
          ]
        },
        {
          "timestamp": 1180,
          "bee_count": 3,
          "avg_confidence": 0.17963052044312158,
          "individual_confidences": [
            0.2783649265766144,
            0.1600062996149063,
            0.10052033513784409
          ]
        },
        {
          "timestamp": 1190,
          "bee_count": 2,
          "avg_confidence": 0.10568925365805626,
          "individual_confidences": [
            0.11024919152259827,
            0.10112931579351425
          ]
        }
      ]
    },
    {
      "segment_number": 5,
      "start_time": 1200,
      "end_time": 1263.7625,
      "duration": 63.762500000000045,
      "total_detections": 16,
      "frames_with_bees": 7,
      "max_simultaneous_bees": 7,
      "detection_rate": 1.0,
      "detections": [
        {
          "timestamp": 1200,
          "bee_count": 1,
          "avg_confidence": 0.10244514793157578,
          "individual_confidences": [
            0.10244514793157578
          ]
        },
        {
          "timestamp": 1210,
          "bee_count": 2,
          "avg_confidence": 0.11172714829444885,
          "individual_confidences": [
            0.11492275446653366,
            0.10853154212236404
          ]
        },
        {
          "timestamp": 1220,
          "bee_count": 1,
          "avg_confidence": 0.12858550250530243,
          "individual_confidences": [
            0.12858550250530243
          ]
        },
        {
          "timestamp": 1230,
          "bee_count": 1,
          "avg_confidence": 0.1233285516500473,
          "individual_confidences": [
            0.1233285516500473
          ]
        },
        {
          "timestamp": 1240,
          "bee_count": 1,
          "avg_confidence": 0.13457819819450378,
          "individual_confidences": [
            0.13457819819450378
          ]
        },
        {
          "timestamp": 1250,
          "bee_count": 7,
          "avg_confidence": 0.14957630527870996,
          "individual_confidences": [
            0.26212385296821594,
            0.1950555294752121,
            0.13668528199195862,
            0.1272311806678772,
            0.11484444886445999,
            0.10664211958646774,
            0.1044517233967781
          ]
        },
        {
          "timestamp": 1260,
          "bee_count": 3,
          "avg_confidence": 0.1826024055480957,
          "individual_confidences": [
            0.28748518228530884,
            0.13786709308624268,
            0.1224549412727356
          ]
        }
      ]
    }
  ],
  "week_info": {
    "week": 5,
    "plant_type": "birds_beak",
    "relative_path": "week_5/day_1/site_2/afternoon/P1000404.MP4"
  }
}